README.md
setup.py
ctkapi/CardRequest.py
ctkapi/ExchangeRequest.py
ctkapi/ExchangeproviderRequests.py
ctkapi/SymbolRequest.py
ctkapi/TransactionRequest.py
ctkapi/UserRequest.py
ctkapi/WalletRequest.py
ctkapi/__init__.py
ctkapi/request.py
ctkapi.egg-info/PKG-INFO
ctkapi.egg-info/SOURCES.txt
ctkapi.egg-info/dependency_links.txt
ctkapi.egg-info/not-zip-safe
ctkapi.egg-info/requires.txt
ctkapi.egg-info/top_level.txt