Metadata-Version: 1.0
Name: ctkapi
Version: 1.0
Summary: Centra SDK for third party integration
Home-page: https://github.com/CentraTech/Centra
Author: centra
Author-email: support@centra.tech
License: MIT
Platform: UNKNOWN
